{
  "season": 2024,
  "round": 4,
  "event_name": "Japanese Grand Prix",
  "event_date": "2024-04-07",
  "target": "quali_top10",
  "target_display": "Qualifying \u2014 driver reaches Q3 (top 10)",
  "model": "features_logit",
  "model_version": "local-20260423101332",
  "generated_at": "2026-04-23T10:13:32+00:00",
  "metrics": {
    "log_loss": 0.26639431802289953,
    "brier": 0.06331726825568156,
    "accuracy_at_0.5": 0.95,
    "positive_rate": 0.5,
    "n": 20,
    "label": "quali_top10_2024_4",
    "ece": 0.22357629616332486
  },
  "summary": {
    "top_driver": {
      "driver": "LEC",
      "team": "Ferrari",
      "p": 0.9395363285623473
    },
    "strongest_team": {
      "team": "Red Bull Racing",
      "mean_p": 0.90632364034104
    },
    "field_average": 0.5194206663050673,
    "prediction_spread": 0.8042617630495501
  },
  "drivers": [
    {
      "driver": "LEC",
      "team": "Ferrari",
      "grid_position": 8,
      "p": 0.9395363285623473,
      "actual": 1,
      "finish_position": 4,
      "top_factors": [
        {
          "feature": "driver_quali_top10_rate_last_10",
          "value": 1.007726497344252
        },
        {
          "feature": "team_points_last_3",
          "value": 0.6902704479087517
        },
        {
          "feature": "driver_finish_last_3",
          "value": 0.4294890606626032
        }
      ],
      "explanation_kind": "linear"
    },
    {
      "driver": "VER",
      "team": "Red Bull Racing",
      "grid_position": 1,
      "p": 0.9301195189648925,
      "actual": 1,
      "finish_position": 1,
      "top_factors": [
        {
          "feature": "driver_quali_top10_rate_last_10",
          "value": 0.8021811381821957
        },
        {
          "feature": "team_points_last_3",
          "value": 0.7807615142635828
        },
        {
          "feature": "driver_points_last_5",
          "value": 0.2738452381501501
        }
      ],
      "explanation_kind": "linear"
    },
    {
      "driver": "PER",
      "team": "Red Bull Racing",
      "grid_position": 2,
      "p": 0.8825277617171875,
      "actual": 1,
      "finish_position": 2,
      "top_factors": [
        {
          "feature": "team_points_last_3",
          "value": 0.7807615142635828
        },
        {
          "feature": "driver_quali_top10_rate_last_10",
          "value": 0.3910904198580827
        },
        {
          "feature": "driver_finish_last_3",
          "value": 0.35859389328870483
        }
      ],
      "explanation_kind": "linear"
    },
    {
      "driver": "PIA",
      "team": "McLaren",
      "grid_position": 6,
      "p": 0.8586601748699522,
      "actual": 1,
      "finish_position": 8,
      "top_factors": [
        {
          "feature": "driver_quali_top10_rate_last_10",
          "value": 0.5966357790201392
        },
        {
          "feature": "team_points_last_3",
          "value": 0.392942658457164
        },
        {
          "feature": "driver_finish_last_3",
          "value": 0.305422517758281
        }
      ],
      "explanation_kind": "linear"
    },
    {
      "driver": "NOR",
      "team": "McLaren",
      "grid_position": 3,
      "p": 0.8516483726677202,
      "actual": 1,
      "finish_position": 5,
      "top_factors": [
        {
          "feature": "driver_quali_top10_rate_last_10",
          "value": 0.5966357790201392
        },
        {
          "feature": "team_points_last_3",
          "value": 0.392942658457164
        },
        {
          "feature": "driver_finish_last_3",
          "value": 0.26997493407133183
        }
      ],
      "explanation_kind": "linear"
    },
    {
      "driver": "SAI",
      "team": "Ferrari",
      "grid_position": 4,
      "p": 0.8469630219443166,
      "actual": 1,
      "finish_position": 3,
      "top_factors": [
        {
          "feature": "team_points_last_3",
          "value": 0.6902704479087517
        },
        {
          "feature": "driver_quali_top10_rate_last_10",
          "value": 0.5966357790201392
        },
        {
          "feature": "driver_quali_gap_last_3",
          "value": 0.14207135696566425
        }
      ],
      "explanation_kind": "linear"
    },
    {
      "driver": "RUS",
      "team": "Mercedes",
      "grid_position": 9,
      "p": 0.8123514787622294,
      "actual": 1,
      "finish_position": 7,
      "top_factors": [
        {
          "feature": "driver_quali_top10_rate_last_10",
          "value": 1.007726497344252
        },
        {
          "feature": "driver_quali_gap_last_3",
          "value": 0.12789196835255887
        },
        {
          "feature": "driver_finish_last_3",
          "value": 0.0927370156365859
        }
      ],
      "explanation_kind": "linear"
    },
    {
      "driver": "ALO",
      "team": "Aston Martin",
      "grid_position": 5,
      "p": 0.7426925032336974,
      "actual": 1,
      "finish_position": 6,
      "top_factors": [
        {
          "feature": "driver_quali_top10_rate_last_10",
          "value": 0.5966357790201392
        },
        {
          "feature": "driver_finish_last_3",
          "value": 0.19907976669743344
        },
        {
          "feature": "driver_quali_gap_last_3",
          "value": 0.1347447320010519
        }
      ],
      "explanation_kind": "linear"
    },
    {
      "driver": "HAM",
      "team": "Mercedes",
      "grid_position": 7,
      "p": 0.6700094276727709,
      "actual": 1,
      "finish_position": 9,
      "top_factors": [
        {
          "feature": "driver_quali_top10_rate_last_10",
          "value": 0.3910904198580827
        },
        {
          "feature": "driver_track_history",
          "value": 0.18744120317157212
        },
        {
          "feature": "driver_quali_gap_last_3",
          "value": 0.09322719053491722
        }
      ],
      "explanation_kind": "linear"
    },
    {
      "driver": "TSU",
      "team": "RB",
      "grid_position": 10,
      "p": 0.4239351130223114,
      "actual": 1,
      "finish_position": 10,
      "top_factors": [
        {
          "feature": "team_points_last_3",
          "value": -0.27927669160729507
        },
        {
          "feature": "driver_quali_top10_rate_last_10",
          "value": -0.22554565762808632
        },
        {
          "feature": "driver_quali_gap_last_3",
          "value": 0.11057780487897322
        }
      ],
      "explanation_kind": "linear"
    },
    {
      "driver": "STR",
      "team": "Aston Martin",
      "grid_position": 16,
      "p": 0.3835079553939992,
      "actual": 0,
      "finish_position": 12,
      "top_factors": [
        {
          "feature": "driver_quali_top10_rate_last_10",
          "value": -0.4310910167901428
        },
        {
          "feature": "driver_track_history",
          "value": -0.13676412012841122
        },
        {
          "feature": "driver_quali_gap_last_3",
          "value": 0.1057662899768397
        }
      ],
      "explanation_kind": "linear"
    },
    {
      "driver": "RIC",
      "team": "RB",
      "grid_position": 11,
      "p": 0.28288861305636426,
      "actual": 0,
      "finish_position": 19,
      "top_factors": [
        {
          "feature": "driver_quali_top10_rate_last_10",
          "value": -0.6366363759521991
        },
        {
          "feature": "team_points_last_3",
          "value": -0.27927669160729507
        },
        {
          "feature": "driver_finish_last_3",
          "value": -0.13767227832858386
        }
      ],
      "explanation_kind": "linear"
    },
    {
      "driver": "HUL",
      "team": "Haas F1 Team",
      "grid_position": 12,
      "p": 0.27733667319348043,
      "actual": 0,
      "finish_position": 11,
      "top_factors": [
        {
          "feature": "driver_quali_top10_rate_last_10",
          "value": -0.6366363759521991
        },
        {
          "feature": "team_points_last_3",
          "value": -0.3439131675750315
        },
        {
          "feature": "driver_points_last_5",
          "value": -0.0825876656066311
        }
      ],
      "explanation_kind": "linear"
    },
    {
      "driver": "GAS",
      "team": "Alpine",
      "grid_position": 17,
      "p": 0.27199025219387485,
      "actual": 0,
      "finish_position": 16,
      "top_factors": [
        {
          "feature": "team_points_last_3",
          "value": -0.39562234834922066
        },
        {
          "feature": "driver_finish_last_3",
          "value": -0.2617388212329061
        },
        {
          "feature": "driver_quali_top10_rate_last_10",
          "value": -0.22554565762808632
        }
      ],
      "explanation_kind": "linear"
    },
    {
      "driver": "OCO",
      "team": "Alpine",
      "grid_position": 15,
      "p": 0.26027678772667157,
      "actual": 0,
      "finish_position": 15,
      "top_factors": [
        {
          "feature": "driver_quali_top10_rate_last_10",
          "value": -0.4310910167901428
        },
        {
          "feature": "team_points_last_3",
          "value": -0.39562234834922066
        },
        {
          "feature": "driver_finish_last_3",
          "value": -0.17311986201553303
        }
      ],
      "explanation_kind": "linear"
    },
    {
      "driver": "BOT",
      "team": "Kick Sauber",
      "grid_position": 13,
      "p": 0.24948346957778963,
      "actual": 0,
      "finish_position": 14,
      "top_factors": [
        {
          "feature": "driver_quali_top10_rate_last_10",
          "value": -0.4310910167901428
        },
        {
          "feature": "team_points_last_3",
          "value": -0.39562234834922066
        },
        {
          "feature": "driver_finish_last_3",
          "value": -0.3326339886068045
        }
      ],
      "explanation_kind": "linear"
    },
    {
      "driver": "MAG",
      "team": "Haas F1 Team",
      "grid_position": 18,
      "p": 0.21633637363196856,
      "actual": 0,
      "finish_position": 13,
      "top_factors": [
        {
          "feature": "driver_quali_top10_rate_last_10",
          "value": -0.6366363759521991
        },
        {
          "feature": "team_points_last_3",
          "value": -0.3439131675750315
        },
        {
          "feature": "driver_finish_last_3",
          "value": -0.19084365385900767
        }
      ],
      "explanation_kind": "linear"
    },
    {
      "driver": "ALB",
      "team": "Williams",
      "grid_position": 14,
      "p": 0.19980129396958907,
      "actual": 0,
      "finish_position": 20,
      "top_factors": [
        {
          "feature": "driver_quali_top10_rate_last_10",
          "value": -0.8421817351142555
        },
        {
          "feature": "team_points_last_3",
          "value": -0.39562234834922066
        },
        {
          "feature": "driver_track_history",
          "value": -0.21781545095340704
        }
      ],
      "explanation_kind": "linear"
    },
    {
      "driver": "ZHO",
      "team": "Kick Sauber",
      "grid_position": 20,
      "p": 0.15307364042738827,
      "actual": 0,
      "finish_position": 18,
      "top_factors": [
        {
          "feature": "driver_quali_top10_rate_last_10",
          "value": -0.8421817351142555
        },
        {
          "feature": "team_points_last_3",
          "value": -0.39562234834922066
        },
        {
          "feature": "driver_finish_last_3",
          "value": -0.3326339886068045
        }
      ],
      "explanation_kind": "linear"
    },
    {
      "driver": "SAR",
      "team": "Williams",
      "grid_position": 19,
      "p": 0.13527456551279712,
      "actual": 0,
      "finish_position": 17,
      "top_factors": [
        {
          "feature": "driver_quali_top10_rate_last_10",
          "value": -0.8421817351142555
        },
        {
          "feature": "team_points_last_3",
          "value": -0.39562234834922066
        },
        {
          "feature": "driver_finish_last_3",
          "value": -0.2617388212329061
        }
      ],
      "explanation_kind": "linear"
    }
  ]
}